termuxgui/__init__.py
termuxgui/activity.py
termuxgui/buffer.py
termuxgui/button.py
termuxgui/checkbox.py
termuxgui/compoundbutton.py
termuxgui/connection.py
termuxgui/edittext.py
termuxgui/event.py
termuxgui/framelayout.py
termuxgui/gridlayout.py
termuxgui/horizontalscrollview.py
termuxgui/imageview.py
termuxgui/linearlayout.py
termuxgui/msg.py
termuxgui/nestedscrollview.py
termuxgui/notification.py
termuxgui/progressbar.py
termuxgui/radiobutton.py
termuxgui/radiogroup.py
termuxgui/remoteviews.py
termuxgui/space.py
termuxgui/spinner.py
termuxgui/swiperefreshlayout.py
termuxgui/switch.py
termuxgui/tablayout.py
termuxgui/task.py
termuxgui/textview.py
termuxgui/togglebutton.py
termuxgui/view.py
termuxgui/viewgroup.py
termuxgui/webview.py
termuxgui/oo/__init__.py
termuxgui/oo/activity.py
termuxgui/oo/button.py
termuxgui/oo/checkbox.py
termuxgui/oo/connection.py
termuxgui/oo/edittext.py
termuxgui/oo/framelayout.py
termuxgui/oo/gridlayout.py
termuxgui/oo/horizontalscrollview.py
termuxgui/oo/imageview.py
termuxgui/oo/linearlayout.py
termuxgui/oo/nestedscrollview.py
termuxgui/oo/progressbar.py
termuxgui/oo/radiobutton.py
termuxgui/oo/radiogroup.py
termuxgui/oo/space.py
termuxgui/oo/spinner.py
termuxgui/oo/swiperefreshlayout.py
termuxgui/oo/switch.py
termuxgui/oo/tablayout.py
termuxgui/oo/textview.py
termuxgui/oo/togglebutton.py
termuxgui/oo/view.py
termuxgui/oo/viewgroup.py
termuxgui/oo/webview.py
termuxgui-0.1.6.dist-info/LICENSE
termuxgui-0.1.6.dist-info/METADATA
termuxgui-0.1.6.dist-info/WHEEL
termuxgui-0.1.6.dist-info/top_level.txt
termuxgui-0.1.6.dist-info/RECORD
