Metadata-Version: 2.1
Name: termuxgui
Version: 0.1.6
Summary: Python bindings for the Termux:GUI plugin.
Home-page: https://github.com/tareksander/termux-gui-python-bindings
Author: Tarek Sander
Project-URL: Bug Tracker, https://github.com/tareksander/termux-gui-python-bindings/issues
Classifier: Programming Language :: Python :: 3
Classifier: License :: OSI Approved :: Mozilla Public License 2.0 (MPL 2.0)
Classifier: Operating System :: Other OS
Requires-Python: >=3.10
License-File: LICENSE
